lutils/__init__.py
lutils/conftest.py
lutils/algos/__init__.py
lutils/algos/kadane.py
lutils/algos/searches/__init__.py
lutils/algos/searches/bst.py
lutils/algos/searches/repatterns.py
lutils/algos/sorts/__init__.py
lutils/algos/sorts/bubblesort.py
lutils/algos/sorts/countingsort.py
lutils/algos/sorts/mergesort.py
lutils/algos/sorts/quicksort.py
lutils/algos/sorts/selectionsort.py
lutils/tests/__init__.py
lutils/tests/units/__init__.py
lutils/tests/units/test_lserver.py
lutils/tests/units/test_lutils.py
lutils/tests/units/test_sorts.py
lutils/utils/__init__.py
lutils/utils/lfiles.py
lutils/utils/lsecure.py
lutils/utils/lserver.py
lutils/utils/lutils.py
lutils-2.11.74.dist-info/LICENSE
lutils-2.11.74.dist-info/METADATA
lutils-2.11.74.dist-info/WHEEL
lutils-2.11.74.dist-info/top_level.txt
lutils-2.11.74.dist-info/RECORD
