Metadata-Version: 2.1
Name: lutils
Version: 2.11.74
Summary: A Public Loitd Python Utility Library
Home-page: https://github.com/loitd/lutils
Author: Tran Duc Loi
Author-email: loitranduc@gmail.com
License: UNKNOWN
Project-URL: Website, https://github.com/loitd/lutils
Project-URL: Documentation, https://github.com/loitd/lutils
Project-URL: Source Code, https://github.com/loitd/lutils
Project-URL: Javascript, https://github.com/loitd/lutilsjs/
Project-URL: Pypi, https://pypi.org/project/lutils/
Keywords: python python3 library utilities loitd printlog printwait telegram python37
Platform: any
Classifier: Development Status :: 5 - Production/Stable
Classifier: Programming Language :: Python :: 3
Classifier: Programming Language :: Python :: 3.7
Classifier: License :: OSI Approved :: MIT License
Classifier: Operating System :: OS Independent
Classifier: Intended Audience :: Developers
Classifier: Environment :: Console
Classifier: Topic :: Software Development :: Libraries :: Python Modules
Classifier: Topic :: Software Development :: Debuggers
Classifier: Topic :: Software Development :: Libraries
Classifier: Topic :: System :: Logging
Classifier: Topic :: System :: Monitoring
Classifier: Natural Language :: English
Requires-Dist: python-telegram-bot (>=12.2.0)
Requires-Dist: paramiko
